[
  {
    "name": "Jon Jones",
    "email": "jJones@petshop.com",
    "password": "password01"
  },
  {
    "name": "Luke Kante",
    "email": "lKante@petshop.com",
    "password": "password02"
  },
  {
    "name": "Joel Matip",
    "email": "jMatip@petshop.com",
    "password": "password03"
  },
  {
    "name": "Berbatov Devis",
    "email": "bDevis@petshop.com",
    "password": "password04"
  },
  {
    "name": " Anthony Rooney",
    "email": "aRooney@petshop.com",
    "password": "password05"
  },
  {
    "name": "Alphonso Robert",
    "email": "aRobert@petshop.com",
    "password": "password06"
  },
  {
    "name": "Lewandewski Sczieni",
    "email": "lSczieni@petshop.com",
    "password": "password07"
  },
  {
    "name": "David Pedro",
    "email": "dPedro@petshop.com",
    "password": "password08"
  },
  {
    "name": "Fred Scott",
    "email": "fScott@petshop.com",
    "password": "password09"
  },
  {
    "name": "Lernantino Bunnici",
    "email": "lBunnici@petshop.com",
    "password": "password10"
  }
]